acondbs/__about__.py
acondbs/__init__.py
acondbs/_logging.py
acondbs/_warnings.py
acondbs/auth/__init__.py
acondbs/blueprint/__init__.py
acondbs/blueprint/graphql_ide/__init__.py
acondbs/blueprint/graphql_ide/graphiql_newer.py
acondbs/blueprint/graphql_ide/graphql_playground.py
acondbs/db/__init__.py
acondbs/db/backup.py
acondbs/db/cmds.py
acondbs/db/conn.py
acondbs/db/ops.py
acondbs/db/sa.py
acondbs/github/__init__.py
acondbs/github/call.py
acondbs/github/ops.py
acondbs/github/query.py
acondbs/migrations/README.md
acondbs/migrations/alembic.ini
acondbs/migrations/env.py
acondbs/migrations/script.py.mako
acondbs/migrations/versions/2023-06-14_14:41-2ed9841987be.py
acondbs/misc/__init__.py
acondbs/misc/cap.py
acondbs/misc/gitb.py
acondbs/misc/lock.py
acondbs/models/__init__.py
acondbs/models/funcs.py
acondbs/models/account/__init__.py
acondbs/models/account/account_admin.py
acondbs/models/github/__init__.py
acondbs/models/github/github_org.py
acondbs/models/github/github_org_membership.py
acondbs/models/github/github_token.py
acondbs/models/github/github_user.py
acondbs/models/misc/__init__.py
acondbs/models/misc/log.py
acondbs/models/product/__init__.py
acondbs/models/product/attribute.py
acondbs/models/product/field.py
acondbs/models/product/product.py
acondbs/models/product/product_file_path.py
acondbs/models/product/product_relation.py
acondbs/models/product/product_relation_type.py
acondbs/models/product/product_type.py
acondbs/models/product/type_field_association.py
acondbs/models/web/__init__.py
acondbs/models/web/web_config.py
acondbs/ops/__init__.py
acondbs/ops/field.py
acondbs/ops/log.py
acondbs/ops/misc.py
acondbs/ops/product.py
acondbs/ops/product_file_path.py
acondbs/ops/product_relation.py
acondbs/ops/product_relation_type.py
acondbs/ops/product_type.py
acondbs/ops/web_config.py
acondbs/schema/__init__.py
acondbs/schema/connection.py
acondbs/schema/filter_.py
acondbs/schema/funcs.py
acondbs/schema/version.py
acondbs/schema/auth/__init__.py
acondbs-0.4.8.dist-info/METADATA
acondbs-0.4.8.dist-info/WHEEL
acondbs-0.4.8.dist-info/licenses/LICENSE
acondbs-0.4.8.dist-info/RECORD
