Metadata-Version: 2.1
Name: acondbs
Version: 0.4.8
Summary: ProductDB back-end API
Project-URL: Homepage, https://github.com/simonsobs/acondbs
Project-URL: Issues, https://github.com/simonsobs/acondbs/issues
Project-URL: Source, https://github.com/simonsobs/acondbs
Author-email: Simons Observatory <so_software@simonsobservatory.org>
License-Expression: MIT
License-File: LICENSE
Classifier: Development Status :: 4 - Beta
Classifier: Intended Audience :: Science/Research
Classifier: License :: OSI Approved :: MIT License
Classifier: Programming Language :: Python :: 3.9
Classifier: Programming Language :: Python :: 3.10
Classifier: Programming Language :: Python :: 3.11
Requires-Python: >=3.9
Requires-Dist: a2wsgi>=1.4
Requires-Dist: cryptography>=3.2
Requires-Dist: flask-cors>=3.0
Requires-Dist: flask-graphql>=2.0
Requires-Dist: flask-migrate>=4.0
Requires-Dist: flask-sqlalchemy>=3.0
Requires-Dist: flask>=2.3
Requires-Dist: gitpython>=3.1
Requires-Dist: graphene-sqlalchemy-filter>=1.10
Requires-Dist: graphene-sqlalchemy>=2.3
Requires-Dist: requests>=2.24
Requires-Dist: sqlalchemy-utils>=0.41
Requires-Dist: sqlalchemy[mypy]<2,>=1.4
Provides-Extra: dev
Requires-Dist: black; extra == 'dev'
Requires-Dist: flake8; extra == 'dev'
Requires-Dist: isort; extra == 'dev'
Requires-Dist: mypy; extra == 'dev'
Requires-Dist: tox; extra == 'dev'
Requires-Dist: twine; extra == 'dev'
Provides-Extra: tests
Requires-Dist: async-asgi-testclient>=1.4.6; extra == 'tests'
Requires-Dist: pytest-asyncio>=0.14; extra == 'tests'
Requires-Dist: pytest-cov>=2.12; extra == 'tests'
Requires-Dist: pytest>=6.2; extra == 'tests'
Requires-Dist: snapshottest>=0.6; extra == 'tests'
Requires-Dist: sqlparse; extra == 'tests'
